boringpy/__init__.py
boringpy/cli/__main__.py
boringpy/cli/app.py
boringpy/cli/commands/__init__.py
boringpy/cli/commands/generate.py
boringpy/cli/commands/init.py
boringpy/cli/utils/__init__.py
boringpy/cli/utils/workspace.py
boringpy/core/__init__.py
boringpy/core/generator.py
boringpy/core/template_engine.py
boringpy/core/uv_manager.py
boringpy/generators/__init__.py
boringpy/generators/api_generator.py
boringpy/templates/README.md
boringpy/templates/api/.dockerignore
boringpy/templates/api/.env.example
boringpy/templates/api/Dockerfile
boringpy/templates/api/Makefile.template
boringpy/templates/api/README.md.template
boringpy/templates/api/alembic.ini.template
boringpy/templates/api/docker-compose.yml.template
boringpy/templates/api/pyproject.toml.template
boringpy/templates/api/template.json
boringpy/templates/api/app/__init__.py
boringpy/templates/api/app/main.py
boringpy/templates/api/app/api/__init__.py
boringpy/templates/api/app/api/deps.py
boringpy/templates/api/app/api/v1/__init__.py
boringpy/templates/api/app/api/v1/endpoints/__init__.py
boringpy/templates/api/app/api/v1/endpoints/health.py
boringpy/templates/api/app/core/__init__.py
boringpy/templates/api/app/core/config.py
boringpy/templates/api/app/core/database.py
boringpy/templates/api/app/core/lifespan.py
boringpy/templates/api/app/core/logger.py
boringpy/templates/api/app/models/__init__.py
boringpy/templates/api/app/models/base.py
boringpy/templates/api/app/models/example.py
boringpy/templates/api/app/services/__init__.py
boringpy/templates/api/migrations/env.py.template
boringpy/templates/api/migrations/script.py.mako
boringpy/templates/api/migrations/versions/.gitkeep
boringpy/templates/api/tests/__init__.py
boringpy/templates/api/tests/test_api.py
boringpy/utils/paths.py
boringpy-0.1.2.dist-info/METADATA
boringpy-0.1.2.dist-info/WHEEL
boringpy-0.1.2.dist-info/entry_points.txt
boringpy-0.1.2.dist-info/licenses/LICENSE
boringpy-0.1.2.dist-info/RECORD
