Metadata-Version: 2.4
Name: boringpy
Version: 0.1.2
Summary: Modern Python scaffolding framework inspired by NestJS CLI - scaffold FastAPI projects with Docker, Alembic, and production-ready structure
Project-URL: Homepage, https://github.com/gverdugo-g14/boringpy14
Project-URL: Repository, https://github.com/gverdugo-g14/boringpy14
Project-URL: Issues, https://github.com/gverdugo-g14/boringpy14/issues
Project-URL: Documentation, https://github.com/gverdugo-g14/boringpy14#readme
Author: BoringPy Contributors
License: MIT
License-File: LICENSE
Keywords: alembic,boilerplate,cli,code-generator,docker,fastapi,generator,nestjs,python,scaffolding
Classifier: Development Status :: 3 - Alpha
Classifier: Environment :: Console
Classifier: Intended Audience :: Developers
Classifier: License :: OSI Approved :: MIT License
Classifier: Operating System :: OS Independent
Classifier: Programming Language :: Python :: 3
Classifier: Programming Language :: Python :: 3.13
Classifier: Topic :: Software Development :: Code Generators
Classifier: Topic :: Software Development :: Libraries :: Application Frameworks
Requires-Python: >=3.13
Requires-Dist: jinja2>=3.1.6
Requires-Dist: rich>=14.2.0
Requires-Dist: typer>=0.21.1
